stuned/__init__.py
stuned/datasets/__init__.py
stuned/datasets/base.py
stuned/datasets/common.py
stuned/datasets/dsprites.py
stuned/datasets/features_labeller.py
stuned/datasets/tiny_imagenet.py
stuned/datasets/utils.py
stuned/run_from_csv/__init__.py
stuned/run_from_csv/__main__.py
stuned/utility/__init__.py
stuned/utility/helpers_for_main.py
stuned/utility/helpers_for_tests.py
stuned/utility/logger.py
stuned/utility/utils.py
stuned-1.0.1.dist-info/LICENSE
stuned-1.0.1.dist-info/METADATA
stuned-1.0.1.dist-info/WHEEL
stuned-1.0.1.dist-info/top_level.txt
stuned-1.0.1.dist-info/RECORD
