Metadata-Version: 2.1
Name: stuned
Version: 1.0.1
Summary: Utility code from STAI (https://scalabletrustworthyai.github.io/)
Home-page: https://github.com/AlexanderRubinstein/STAI-tuned
Author: Alexander Rubinstein
Author-email: rubalex14@gmail.com
Project-URL: Bug Tracker, https://github.com/AlexanderRubinstein/STAI-tuned/issues
Project-URL: repository, https://github.com/AlexanderRubinstein/STAI-tuned
Classifier: Programming Language :: Python :: 3
Classifier: License :: OSI Approved :: MIT License
Classifier: Operating System :: OS Independent
Requires-Python: >=3.10
License-File: LICENSE
Requires-Dist: absl-py (==1.2.0)
Requires-Dist: accelerate (==0.17.1)
Requires-Dist: aiohttp (==3.8.4)
Requires-Dist: aiosignal (==1.3.1)
Requires-Dist: albumentations (==1.3.0)
Requires-Dist: antlr4-python3-runtime (==4.8)
Requires-Dist: appdirs (==1.4.4)
Requires-Dist: argon2-cffi (==21.3.0)
Requires-Dist: argon2-cffi-bindings (==21.2.0)
Requires-Dist: asttokens (==2.0.8)
Requires-Dist: astunparse (==1.6.3)
Requires-Dist: async-timeout (==4.0.2)
Requires-Dist: attrs (==22.1.0)
Requires-Dist: backcall (==0.2.0)
Requires-Dist: beautifulsoup4 (==4.11.1)
Requires-Dist: bleach (==5.0.1)
Requires-Dist: cachetools (==5.2.0)
Requires-Dist: cffi (==1.15.1)
Requires-Dist: charset-normalizer (==2.1.0)
Requires-Dist: click (==8.1.3)
Requires-Dist: cryptography (==39.0.1)
Requires-Dist: cycler (==0.11.0)
Requires-Dist: debugpy (==1.6.3)
Requires-Dist: decorator (==5.1.1)
Requires-Dist: deepdiff (==5.8.1)
Requires-Dist: defusedxml (==0.7.1)
Requires-Dist: diffusers (==0.14.0)
Requires-Dist: docker-pycreds (==0.4.0)
Requires-Dist: einops (==0.3.0)
Requires-Dist: entrypoints (==0.4)
Requires-Dist: et-xmlfile (==1.1.0)
Requires-Dist: execnet (==1.9.0)
Requires-Dist: executing (==1.0.0)
Requires-Dist: fastjsonschema (==2.16.1)
Requires-Dist: filelock (==3.8.0)
Requires-Dist: flatbuffers (==23.1.21)
Requires-Dist: fonttools (==4.36.0)
Requires-Dist: frozenlist (==1.3.3)
Requires-Dist: fsspec (==2023.3.0)
Requires-Dist: ftfy (==6.1.1)
Requires-Dist: future (==0.18.3)
Requires-Dist: gast (==0.4.0)
Requires-Dist: gdown (==4.5.1)
Requires-Dist: gitdb (==4.0.9)
Requires-Dist: GitPython (==3.1.27)
Requires-Dist: google-api-core (==2.11.0)
Requires-Dist: google-api-python-client (==2.79.0)
Requires-Dist: google-auth (==2.16.1)
Requires-Dist: google-auth-httplib2 (==0.1.0)
Requires-Dist: google-auth-oauthlib (==0.4.6)
Requires-Dist: google-pasta (==0.2.0)
Requires-Dist: googleapis-common-protos (==1.58.0)
Requires-Dist: grpcio (==1.51.3)
Requires-Dist: gspread (==5.7.2)
Requires-Dist: h5pickle (==0.4.2)
Requires-Dist: h5py (==3.7.0)
Requires-Dist: httplib2 (==0.21.0)
Requires-Dist: huggingface-hub (==0.13.3)
Requires-Dist: idna (==3.3)
Requires-Dist: imageio (==2.21.1)
Requires-Dist: importlib-metadata (==6.1.0)
Requires-Dist: iniconfig (==1.1.1)
Requires-Dist: ipykernel (==6.15.2)
Requires-Dist: ipython (==8.4.0)
Requires-Dist: ipython-genutils (==0.2.0)
Requires-Dist: ipywidgets (==8.0.1)
Requires-Dist: jedi (==0.18.1)
Requires-Dist: Jinja2 (==3.1.2)
Requires-Dist: joblib (==1.1.0)
Requires-Dist: jsonschema (==4.14.0)
Requires-Dist: jupyter (==1.0.0)
Requires-Dist: jupyter-console (==6.4.4)
Requires-Dist: jupyter-core (==4.11.1)
Requires-Dist: jupyter-client (==7.3.5)
Requires-Dist: jupyterlab-pygments (==0.2.2)
Requires-Dist: jupyterlab-widgets (==3.0.2)
Requires-Dist: keras (==2.11.0)
Requires-Dist: Keras-Preprocessing (==1.1.2)
Requires-Dist: kiwisolver (==1.4.4)
Requires-Dist: kornia (==0.6.0)
Requires-Dist: libclang (==14.0.6)
Requires-Dist: lxml (==4.9.1)
Requires-Dist: Markdown (==3.4.1)
Requires-Dist: MarkupSafe (==2.1.1)
Requires-Dist: matplotlib (==3.5.3)
Requires-Dist: matplotlib-inline (==0.1.6)
Requires-Dist: mistune (==2.0.4)
Requires-Dist: multidict (==6.0.4)
Requires-Dist: nbclient (==0.6.7)
Requires-Dist: nbconvert (==7.0.0)
Requires-Dist: nbformat (==5.4.0)
Requires-Dist: nest-asyncio (==1.5.5)
Requires-Dist: networkx (==2.8.5)
Requires-Dist: notebook (==6.4.12)
Requires-Dist: numpy (==1.23.2)
Requires-Dist: nvidia-cublas-cu11 (==11.10.3.66)
Requires-Dist: nvidia-cuda-nvrtc-cu11 (==11.7.99)
Requires-Dist: nvidia-cuda-runtime-cu11 (==11.7.99)
Requires-Dist: nvidia-cudnn-cu11 (==8.5.0.96)
Requires-Dist: oauth2client (==4.1.3)
Requires-Dist: oauthlib (==3.2.0)
Requires-Dist: omegaconf (==2.1.1)
Requires-Dist: open-clip-torch (==2.0.2)
Requires-Dist: opencv-python (==4.6.0.66)
Requires-Dist: opencv-python-headless (==4.7.0.72)
Requires-Dist: openpyxl (==3.1.1)
Requires-Dist: opt-einsum (==3.3.0)
Requires-Dist: ordered-set (==4.1.0)
Requires-Dist: packaging (==21.3)
Requires-Dist: pandas (==1.4.3)
Requires-Dist: pandocfilters (==1.5.0)
Requires-Dist: parso (==0.8.3)
Requires-Dist: pathtools (==0.1.2)
Requires-Dist: pexpect (==4.8.0)
Requires-Dist: pickleshare (==0.7.5)
Requires-Dist: Pillow (==9.2.0)
Requires-Dist: pluggy (==1.0.0)
Requires-Dist: prometheus-client (==0.14.1)
Requires-Dist: promise (==2.3)
Requires-Dist: prompt-toolkit (==3.0.30)
Requires-Dist: protobuf (==3.19.6)
Requires-Dist: psutil (==5.9.1)
Requires-Dist: ptyprocess (==0.7.0)
Requires-Dist: pure-eval (==0.2.2)
Requires-Dist: py (==1.11.0)
Requires-Dist: pyasn1 (==0.4.8)
Requires-Dist: pyasn1-modules (==0.2.8)
Requires-Dist: pycparser (==2.21)
Requires-Dist: pyDeprecate (==0.3.1)
Requires-Dist: PyDrive2 (==1.15.1)
Requires-Dist: Pygments (==2.13.0)
Requires-Dist: pyOpenSSL (==23.0.0)
Requires-Dist: pyparsing (==3.0.9)
Requires-Dist: pyrsistent (==0.18.1)
Requires-Dist: PySocks (==1.7.1)
Requires-Dist: pytest (==7.1.3)
Requires-Dist: pytest-xdist (==3.0.2)
Requires-Dist: python-dateutil (==2.8.2)
Requires-Dist: pytorch-lightning (==1.4.2)
Requires-Dist: pytz (==2022.2.1)
Requires-Dist: PyWavelets (==1.3.0)
Requires-Dist: PyYAML (==6.0)
Requires-Dist: pyzmq (==23.2.1)
Requires-Dist: qtconsole (==5.3.2)
Requires-Dist: QtPy (==2.2.0)
Requires-Dist: qudida (==0.0.4)
Requires-Dist: regex (==2022.10.31)
Requires-Dist: requests (==2.28.1)
Requires-Dist: requests-oauthlib (==1.3.1)
Requires-Dist: rsa (==4.9)
Requires-Dist: scikit-image (==0.19.3)
Requires-Dist: scikit-learn (==1.1.2)
Requires-Dist: scipy (==1.9.0)
Requires-Dist: seaborn (==0.11.2)
Requires-Dist: Send2Trash (==1.8.0)
Requires-Dist: sentry-sdk (==1.9.5)
Requires-Dist: setproctitle (==1.3.2)
Requires-Dist: shortuuid (==1.0.9)
Requires-Dist: six (==1.16.0)
Requires-Dist: sklearn (==0.0)
Requires-Dist: smmap (==5.0.0)
Requires-Dist: soupsieve (==2.3.2.post1)
Requires-Dist: stable-diffusion-sdkit (==2.1.4)
Requires-Dist: stack-data (==0.5.0)
Requires-Dist: tensorboard (==2.11.2)
Requires-Dist: tensorboard-data-server (==0.6.1)
Requires-Dist: tensorboard-plugin-wit (==1.8.1)
Requires-Dist: tensorflow (==2.11.0)
Requires-Dist: tensorflow-estimator (==2.11.0)
Requires-Dist: tensorflow-io (==0.31.0)
Requires-Dist: tensorflow-io-gcs-filesystem (==0.31.0)
Requires-Dist: termcolor (==2.0.1)
Requires-Dist: terminado (==0.15.0)
Requires-Dist: test-tube (==0.7.5)
Requires-Dist: threadpoolctl (==3.1.0)
Requires-Dist: tifffile (==2022.8.12)
Requires-Dist: timm (==0.6.7)
Requires-Dist: tinycss2 (==1.1.1)
Requires-Dist: tokenizers (==0.13.2)
Requires-Dist: tomli (==2.0.1)
Requires-Dist: torch (==1.13.1)
Requires-Dist: torchmetrics (==0.6.0)
Requires-Dist: torchvision (==0.14.1)
Requires-Dist: tornado (==6.2)
Requires-Dist: tqdm (==4.64.0)
Requires-Dist: traitlets (==5.3.0)
Requires-Dist: transformers (==4.26.1)
Requires-Dist: typing-extensions (==4.3.0)
Requires-Dist: uritemplate (==4.1.1)
Requires-Dist: urllib3 (==1.26.11)
Requires-Dist: wandb (==0.13.10)
Requires-Dist: watchdog (==3.0.0)
Requires-Dist: wcwidth (==0.2.5)
Requires-Dist: webencodings (==0.5.1)
Requires-Dist: Werkzeug (==2.2.2)
Requires-Dist: widgetsnbextension (==4.0.2)
Requires-Dist: wrapt (==1.14.1)
Requires-Dist: yarl (==1.8.2)
Requires-Dist: zipp (==3.15.0)
